env_to_class/__init__.py
env_to_class/main.py
env_to_class-1.1.0.dist-info/WHEEL
env_to_class-1.1.0.dist-info/METADATA
env_to_class-1.1.0.dist-info/RECORD
