Metadata-Version: 2.1
Name: env-to-class
Version: 1.1.0
Summary: Enviroment variables to class object with checking for the presence of parameters
Author: to101
Author-email: to101kv@gmail.com
Requires-Python: >=3.1,<4.0
Classifier: Programming Language :: Python :: 3
Classifier: Programming Language :: Python :: 3.10
Classifier: Programming Language :: Python :: 3.4
Classifier: Programming Language :: Python :: 3.5
Classifier: Programming Language :: Python :: 3.6
Classifier: Programming Language :: Python :: 3.7
Classifier: Programming Language :: Python :: 3.8
Classifier: Programming Language :: Python :: 3.9
